<annotation>
	<folder></folder>
	<filename>IMG_4184-MOV_out0036_png.rf.026d8391468bc386f4b4e5ac39fa39e6.jpg</filename>
	<path>IMG_4184-MOV_out0036_png.rf.026d8391468bc386f4b4e5ac39fa39e6.jpg</path>
	<source>
		<database>roboflow.com</database>
	</source>
	<size>
		<width>640</width>
		<height>640</height>
		<depth>3</depth>
	</size>
	<segmented>0</segmented>
	<object>
		<name>W.201b</name>
		<pose>Unspecified</pose>
		<truncated>0</truncated>
		<difficult>0</difficult>
		<occluded>0</occluded>
		<bndbox>
			<xmin>124</xmin>
			<xmax>134</xmax>
			<ymin>293</ymin>
			<ymax>307</ymax>
		</bndbox>
	</object>
	<object>
		<name>P.131a</name>
		<pose>Unspecified</pose>
		<truncated>0</truncated>
		<difficult>0</difficult>
		<occluded>0</occluded>
		<bndbox>
			<xmin>188</xmin>
			<xmax>212</xmax>
			<ymin>248</ymin>
			<ymax>290</ymax>
		</bndbox>
	</object>
	<object>
		<name>P.130</name>
		<pose>Unspecified</pose>
		<truncated>0</truncated>
		<difficult>0</difficult>
		<occluded>0</occluded>
		<bndbox>
			<xmin>104</xmin>
			<xmax>111</xmax>
			<ymin>316</ymin>
			<ymax>329</ymax>
		</bndbox>
	</object>
</annotation>
